kektordb_client/__init__.py
kektordb_client/client.py
kektordb_client/langchain.py
kektordb_client-0.4.0.dist-info/METADATA
kektordb_client-0.4.0.dist-info/WHEEL
kektordb_client-0.4.0.dist-info/top_level.txt
kektordb_client-0.4.0.dist-info/RECORD
