Metadata-Version: 2.1
Name: kektordb-client
Version: 0.4.0
Summary: An official Python client for KektorDB. An in-memory Vector Database & AI Gateway written in Go. Supports HNSW, Hybrid Search (BM25), GraphRAG context, a built-in RAG Pipeline, and can be embedded directly into your apps. 
Home-page: https://github.com/sanonone/kektordb
Author: Sanonone
Author-email: fedeld023@gmail.com
Classifier: Programming Language :: Python :: 3
Classifier: License :: OSI Approved :: Apache Software License
Classifier: Operating System :: OS Independent
Classifier: Topic :: Database
Classifier: Topic :: Scientific/Engineering :: Artificial Intelligence
Requires-Python: >=3.7
Requires-Dist: numpy
Requires-Dist: requests
